jasper/__init__.py
lotus/__init__.py
lotus_engine/__init__.py
lotus_engine-0.0.2.dist-info/LICENSE
lotus_engine-0.0.2.dist-info/METADATA
lotus_engine-0.0.2.dist-info/WHEEL
lotus_engine-0.0.2.dist-info/top_level.txt
lotus_engine-0.0.2.dist-info/RECORD
