Metadata-Version: 2.1
Name: lotus-engine
Version: 0.0.2
Summary: A android reverse tool
Home-page: http://github.com/vforkliu/lotus
Author: forkliu
Author-email: vforkliu@gmail.com
License: UNKNOWN
Keywords: android,unicorn,emulator
Platform: UNKNOWN
Requires-Python: >=3
Requires-Dist: unicorn (==1.0.3)
